{"topic": "mission_start", "data": null, "time" : 1}
{"topic": "move", "data": "0", "time" : 2}
{"topic": "inspect", "data": "0", "time" : 3}
{"topic": "radiation_level", "data": "Green", "time" : 4}
{"topic": "move", "data": "2", "time" : 5}
{"topic": "inspect", "data": "2", "time" : 6}
{"topic": "radiation_level", "data": "Green", "time" : 7}
{"topic": "move", "data": "1", "time" : 8}
{"topic": "inspect", "data": "1", "time" : 9}
{"topic": "radiation_level", "data": "Green", "time" : 10}
{"topic": "move", "data": "3", "time" : 11}
{"topic": "inspect", "data": "3", "time" : 12}
{"topic": "radiation_level", "data": "Green", "time" : 13}
{"topic": "move", "data": "4", "time" : 14}
{"topic": "inspect", "data": "4", "time" : 15}
{"topic": "radiation_level", "data": "Green", "time" : 16}
{"topic": "move", "data": "5", "time" : 17}
{"topic": "inspect", "data": "5", "time" : 18}
{"topic": "radiation_level", "data": "Green", "time" : 19}
{"topic": "move", "data": "6", "time" : 20}
{"topic": "inspect", "data": "6", "time" : 21}
{"topic": "radiation_level", "data": "Green", "time" : 22}
{"topic": "move", "data": "7", "time" : 23}
{"topic": "inspect", "data": "7", "time" : 24}
{"topic": "radiation_level", "data": "Green", "time" : 25}
{"topic": "move", "data": "8", "time" : 26}
{"topic": "inspect", "data": "8", "time" : 27}
{"topic": "radiation_level", "data": "Green", "time" : 28}
{"topic": "move", "data": "9", "time" : 29}
{"topic": "inspect", "data": "9", "time" : 30}
{"topic": "radiation_level", "data": "Green", "time" : 31}
{"topic": "move", "data": "10", "time" : 32}
{"topic": "inspect", "data": "10", "time" : 33}
{"topic": "radiation_level", "data": "Green", "time" : 34}
{"topic": "move", "data": "11", "time" : 35}
{"topic": "inspect", "data": "11", "time" : 36}
{"topic": "radiation_level", "data": "Green", "time" : 37}
{"topic": "move", "data": "12", "time" : 38}
{"topic": "inspect", "data": "12", "time" : 39}
{"topic": "radiation_level", "data": "Green", "time" : 40}
{"topic": "mission_complete", "data": null, "time" : 41}
{"topic": "move", "data": "0", "time" : 42}
